csrd_models/__init__.py
csrd_models/entity/__init__.py
csrd_models/entity/_schema.py
csrd_models/entity/entity.py
csrd_models-0.1.10.dist-info/METADATA
csrd_models-0.1.10.dist-info/WHEEL
csrd_models-0.1.10.dist-info/RECORD
