Metadata-Version: 2.1
Name: csrd-models
Version: 0.1.10
Summary: models lib
Author: aaron
Author-email: aaron@frostmn.com
Requires-Python: >=3.12,<4.0
Classifier: Programming Language :: Python :: 3
Classifier: Programming Language :: Python :: 3.12
Classifier: Programming Language :: Python :: 3.13
Requires-Dist: csrd-utils (>=0.1,<0.2)
Requires-Dist: pre-commit (>=3.8.0,<4.0.0)
